backtesting/__init__.py
backtesting/_nbdev.py
backtesting/core.py
simpler_backtest/__init__.py
simpler_backtest/_nbdev.py
simpler_backtest/core.py
simpler_backtest/indicators.py
simpler_backtest-0.0.1.dist-info/LICENSE
simpler_backtest-0.0.1.dist-info/METADATA
simpler_backtest-0.0.1.dist-info/WHEEL
simpler_backtest-0.0.1.dist-info/entry_points.txt
simpler_backtest-0.0.1.dist-info/top_level.txt
simpler_backtest-0.0.1.dist-info/RECORD
